{
    "key": "group_620837106a333",
    "title": "Block: Card",
    "fields": [
        {
            "key": "field_63ae39b9b0d99",
            "label": "Layout",
            "name": "layout",
            "aria-label": "",
            "type": "clone",
            "instructions": "",
            "required": 0,
            "conditional_logic": [
                [
                    {
                        "field": "field_63b7d07a1e171",
                        "operator": "!=",
                        "value": "1"
                    }
                ]
            ],
            "wrapper": {
                "width": "",
                "class": "",
                "id": ""
            },
            "admin_only": 0,
            "clone": [
                "group_63ae37b32b4cc"
            ],
            "display": "group",
            "layout": "block",
            "prefix_label": 0,
            "prefix_name": 1
        },
        {
            "key": "field_63b882b676a06",
            "label": "Layout",
            "name": "horizontal_layout",
            "aria-label": "",
            "type": "clone",
            "instructions": "",
            "required": 0,
            "conditional_logic": [
                [
                    {
                        "field": "field_63b7d07a1e171",
                        "operator": "==",
                        "value": "1"
                    }
                ]
            ],
            "wrapper": {
                "width": "",
                "class": "",
                "id": ""
            },
            "admin_only": 0,
            "clone": [
                "group_63b85bfeb1d9e"
            ],
            "display": "group",
            "layout": "block",
            "prefix_label": 0,
            "prefix_name": 1
        },
        {
            "key": "field_6397c936481ae",
            "label": "Background Color",
            "name": "card_bg_color",
            "aria-label": "",
            "type": "clone",
            "instructions": "",
            "required": 0,
            "conditional_logic": 0,
            "wrapper": {
                "width": "",
                "class": "",
                "id": ""
            },
            "admin_only": 0,
            "clone": [
                "group_634653996a829"
            ],
            "display": "group",
            "layout": "block",
            "prefix_label": 0,
            "prefix_name": 1
        },
        {
            "key": "field_6399385883368",
            "label": "Remove Card Border",
            "name": "remove_card_border",
            "aria-label": "",
            "type": "true_false",
            "instructions": "",
            "required": 0,
            "conditional_logic": 0,
            "wrapper": {
                "width": "",
                "class": "",
                "id": ""
            },
            "admin_only": 0,
            "message": "",
            "default_value": 0,
            "ui_on_text": "",
            "ui_off_text": "",
            "ui": 1
        },
        {
            "key": "field_656c15621be50",
            "label": "Card Border",
            "name": "card_border",
            "aria-label": "",
            "type": "clone",
            "instructions": "",
            "required": 0,
            "conditional_logic": [
                [
                    {
                        "field": "field_6399385883368",
                        "operator": "!=",
                        "value": "1"
                    }
                ]
            ],
            "wrapper": {
                "width": "",
                "class": "",
                "id": ""
            },
            "admin_only": 0,
            "clone": [
                "group_634db7f7df7b1"
            ],
            "display": "group",
            "layout": "block",
            "prefix_label": 0,
            "prefix_name": 1
        },
        {
            "key": "field_6397c907481ad",
            "label": "Text Color",
            "name": "card_text_color",
            "aria-label": "",
            "type": "clone",
            "instructions": "",
            "required": 0,
            "conditional_logic": 0,
            "wrapper": {
                "width": "",
                "class": "",
                "id": ""
            },
            "admin_only": 0,
            "clone": [
                "group_6346513f54d9a"
            ],
            "display": "group",
            "layout": "block",
            "prefix_label": 0,
            "prefix_name": 1
        },
        {
            "key": "field_63994e661afbf",
            "label": "Inherit Text Color",
            "name": "inherit_text_color",
            "aria-label": "",
            "type": "true_false",
            "instructions": "Resets card label, title and subtitle so that it inherits the color from its parent.",
            "required": 0,
            "conditional_logic": [
                [
                    {
                        "field": "field_624a435523a11",
                        "operator": "!=empty"
                    }
                ],
                [
                    {
                        "field": "field_620837205a887",
                        "operator": "!=empty"
                    }
                ],
                [
                    {
                        "field": "field_6208373c5a888",
                        "operator": "!=empty"
                    }
                ]
            ],
            "wrapper": {
                "width": "",
                "class": "",
                "id": ""
            },
            "admin_only": 0,
            "message": "",
            "default_value": 0,
            "ui_on_text": "",
            "ui_off_text": "",
            "ui": 1
        },
        {
            "key": "field_63993cce97a30",
            "label": "Text Alignment",
            "name": "text_align",
            "aria-label": "",
            "type": "select",
            "instructions": "",
            "required": 0,
            "conditional_logic": 0,
            "wrapper": {
                "width": "",
                "class": "",
                "id": ""
            },
            "admin_only": 0,
            "choices": {
                "null": "Left",
                "center": "Center",
                "end": "Right"
            },
            "default_value": "null",
            "return_format": "value",
            "multiple": 0,
            "allow_null": 0,
            "ui": 0,
            "ajax": 0,
            "placeholder": ""
        },
        {
            "key": "field_63993eff79cc3",
            "label": "Icon",
            "name": "card_icon",
            "aria-label": "",
            "type": "clone",
            "instructions": "",
            "required": 0,
            "conditional_logic": 0,
            "wrapper": {
                "width": "",
                "class": "",
                "id": ""
            },
            "admin_only": 0,
            "clone": [
                "field_635406cfd4432",
                "field_635406cfd4433",
                "field_635406cfd4434",
                "field_635406cfd4435",
                "field_635406cfd4437",
                "field_635406cfd4438",
                "field_6354b94f6bf6c",
                "field_6354ba126bf6d"
            ],
            "display": "group",
            "layout": "block",
            "prefix_label": 0,
            "prefix_name": 1
        },
        {
            "key": "field_624a435523a11",
            "label": "Label",
            "name": "label",
            "aria-label": "",
            "type": "text",
            "instructions": "",
            "required": 0,
            "conditional_logic": 0,
            "wrapper": {
                "width": "",
                "class": "",
                "id": ""
            },
            "default_value": "",
            "placeholder": "",
            "prepend": "",
            "append": "",
            "maxlength": ""
        },
        {
            "key": "field_620837205a887",
            "label": "Title",
            "name": "card_title",
            "aria-label": "",
            "type": "text",
            "instructions": "",
            "required": 0,
            "conditional_logic": 0,
            "wrapper": {
                "width": "",
                "class": "",
                "id": ""
            },
            "default_value": "",
            "placeholder": "",
            "prepend": "",
            "append": "",
            "maxlength": ""
        },
        {
            "key": "field_6208373c5a888",
            "label": "Subtitle",
            "name": "subtitle",
            "aria-label": "",
            "type": "text",
            "instructions": "",
            "required": 0,
            "conditional_logic": 0,
            "wrapper": {
                "width": "",
                "class": "",
                "id": ""
            },
            "default_value": "",
            "placeholder": "",
            "prepend": "",
            "append": "",
            "maxlength": ""
        },
        {
            "key": "field_620837455a889",
            "label": "Body",
            "name": "body",
            "aria-label": "",
            "type": "wysiwyg",
            "instructions": "",
            "required": 0,
            "conditional_logic": 0,
            "wrapper": {
                "width": "",
                "class": "",
                "id": ""
            },
            "default_value": "",
            "tabs": "all",
            "toolbar": "full",
            "media_upload": 1,
            "delay": 0
        },
        {
            "key": "field_6208378b5a88a",
            "label": "Link",
            "name": "link",
            "aria-label": "",
            "type": "link",
            "instructions": "",
            "required": 0,
            "conditional_logic": 0,
            "wrapper": {
                "width": "",
                "class": "",
                "id": ""
            },
            "return_format": "array"
        },
        {
            "key": "field_6208379e5a88b",
            "label": "Link Card",
            "name": "link_card",
            "aria-label": "",
            "type": "true_false",
            "instructions": "WARNING: Using links inside of a linked card will break.",
            "required": 0,
            "conditional_logic": 0,
            "wrapper": {
                "width": "",
                "class": "",
                "id": ""
            },
            "message": "",
            "default_value": 0,
            "ui": 1,
            "ui_on_text": "",
            "ui_off_text": ""
        },
        {
            "key": "field_68dddba7eb327",
            "label": "Vertically Center Content",
            "name": "vertically_center_content",
            "aria-label": "",
            "type": "true_false",
            "instructions": "",
            "required": 0,
            "conditional_logic": 0,
            "wrapper": {
                "width": "",
                "class": "",
                "id": ""
            },
            "admin_only": 0,
            "message": "",
            "default_value": 0,
            "ui_on_text": "",
            "ui_off_text": "",
            "ui": 1
        },
        {
            "key": "field_63980a5e74085",
            "label": "Background Image",
            "name": "card_bg_image",
            "aria-label": "",
            "type": "clone",
            "instructions": "",
            "required": 0,
            "conditional_logic": 0,
            "wrapper": {
                "width": "",
                "class": "",
                "id": ""
            },
            "admin_only": 0,
            "clone": [
                "group_636871db82c48"
            ],
            "display": "group",
            "layout": "block",
            "prefix_label": 0,
            "prefix_name": 1
        },
        {
            "key": "field_6397fc7651c88",
            "label": "Include Image",
            "name": "include_image",
            "aria-label": "",
            "type": "true_false",
            "instructions": "",
            "required": 0,
            "conditional_logic": 0,
            "wrapper": {
                "width": "",
                "class": "",
                "id": ""
            },
            "admin_only": 0,
            "message": "",
            "default_value": 1,
            "ui_on_text": "",
            "ui_off_text": "",
            "ui": 1
        },
        {
            "key": "field_6397e952b77c6",
            "label": "Image",
            "name": "image",
            "aria-label": "",
            "type": "clone",
            "instructions": "",
            "required": 0,
            "conditional_logic": [
                [
                    {
                        "field": "field_6397fc7651c88",
                        "operator": "==",
                        "value": "1"
                    }
                ]
            ],
            "wrapper": {
                "width": "",
                "class": "",
                "id": ""
            },
            "admin_only": 0,
            "clone": [
                "group_6393b53879908"
            ],
            "display": "group",
            "layout": "block",
            "prefix_label": 0,
            "prefix_name": 1
        },
        {
            "key": "field_6224f315399a4",
            "label": "Image Position",
            "name": "image_position",
            "aria-label": "",
            "type": "radio",
            "instructions": "",
            "required": 0,
            "conditional_logic": [
                [
                    {
                        "field": "field_6397fc7651c88",
                        "operator": "==",
                        "value": "1"
                    }
                ]
            ],
            "wrapper": {
                "width": "",
                "class": "",
                "id": ""
            },
            "admin_only": 0,
            "choices": {
                "top": "Top",
                "bottom": "Bottom"
            },
            "default_value": "top",
            "return_format": "value",
            "allow_null": 0,
            "other_choice": 0,
            "layout": "horizontal",
            "save_other_choice": 0
        },
        {
            "key": "field_6397e8ebb5465",
            "label": "Image Overlay",
            "name": "image_overlay",
            "aria-label": "",
            "type": "true_false",
            "instructions": "Image overlay cannot be used with overlay text or flip card.",
            "required": 0,
            "conditional_logic": [
                [
                    {
                        "field": "field_6397fc7651c88",
                        "operator": "==",
                        "value": "1"
                    },
                    {
                        "field": "field_6367f8db8d9ec",
                        "operator": "!=",
                        "value": "1"
                    },
                    {
                        "field": "field_6397e924b5466",
                        "operator": "==empty"
                    }
                ]
            ],
            "wrapper": {
                "width": "",
                "class": "",
                "id": ""
            },
            "admin_only": 0,
            "message": "",
            "default_value": 0,
            "ui_on_text": "",
            "ui_off_text": "",
            "ui": 1
        },
        {
            "key": "field_6397e924b5466",
            "label": "Image Overlay Text",
            "name": "image_overlay_text",
            "aria-label": "",
            "type": "text",
            "instructions": "Overlay text cannot be used with image overlay.",
            "required": 0,
            "conditional_logic": [
                [
                    {
                        "field": "field_6397fc7651c88",
                        "operator": "==",
                        "value": "1"
                    },
                    {
                        "field": "field_6397e8ebb5465",
                        "operator": "!=",
                        "value": "1"
                    }
                ]
            ],
            "wrapper": {
                "width": "",
                "class": "",
                "id": ""
            },
            "admin_only": 0,
            "default_value": "",
            "maxlength": "",
            "placeholder": "",
            "prepend": "",
            "append": ""
        },
        {
            "key": "field_622511f6db03f",
            "label": "Show Button",
            "name": "show_button",
            "aria-label": "",
            "type": "true_false",
            "instructions": "",
            "required": 0,
            "conditional_logic": 0,
            "wrapper": {
                "width": "",
                "class": "",
                "id": ""
            },
            "message": "",
            "default_value": 0,
            "ui": 1,
            "ui_on_text": "",
            "ui_off_text": ""
        },
        {
            "key": "field_634ec3d02152f",
            "label": "Button",
            "name": "button",
            "aria-label": "",
            "type": "clone",
            "instructions": "",
            "required": 0,
            "conditional_logic": [
                [
                    {
                        "field": "field_622511f6db03f",
                        "operator": "==",
                        "value": "1"
                    }
                ]
            ],
            "wrapper": {
                "width": "",
                "class": "",
                "id": ""
            },
            "admin_only": 0,
            "clone": [
                "field_6363537ea6633",
                "field_634b9262e0f68",
                "field_6376898a62ebf",
                "field_634b9262e0f6d",
                "field_634b9262e0f6e",
                "field_634b9262e0f6f",
                "field_634dca232b6dd",
                "field_63766afd9f3fa",
                "field_634dca5c2b6de",
                "field_634dcab72b6df",
                "field_634dcb8c637ec",
                "field_634dcaf72b6e0",
                "field_634dcb292b6e1",
                "field_634dc9c42b6dc",
                "field_634b9262e0f72",
                "field_634b9262e0f73",
                "field_634b9262e0f74",
                "field_634b9262e0f75",
                "field_634b9262e0f7d",
                "field_634b9262e0f7e",
                "field_634b9262e0f7f",
                "field_634b9262e0f80",
                "field_634b9262e0f7b",
                "field_634b9262e0f81",
                "field_634b9262e0f82",
                "field_634b9262e0f83",
                "field_634b9262e0f84",
                "field_634b9262e0f85",
                "field_634b9262e0f86"
            ],
            "display": "group",
            "layout": "block",
            "prefix_label": 0,
            "prefix_name": 1
        },
        {
            "key": "field_6225a8a52f16d",
            "label": "Trigger Modal",
            "name": "trigger_modal",
            "aria-label": "",
            "type": "true_false",
            "instructions": "",
            "required": 0,
            "conditional_logic": [
                [
                    {
                        "field": "field_6208378b5a88a",
                        "operator": "!=empty"
                    }
                ],
                [
                    {
                        "field": "field_6208379e5a88b",
                        "operator": "==",
                        "value": "1"
                    }
                ],
                [
                    {
                        "field": "field_622511f6db03f",
                        "operator": "==",
                        "value": "1"
                    }
                ]
            ],
            "wrapper": {
                "width": "",
                "class": "",
                "id": ""
            },
            "message": "",
            "default_value": 0,
            "ui": 1,
            "ui_on_text": "",
            "ui_off_text": ""
        },
        {
            "key": "field_6225a9122f16e",
            "label": "Modal ID",
            "name": "modal_id",
            "aria-label": "",
            "type": "text",
            "instructions": "",
            "required": 1,
            "conditional_logic": [
                [
                    {
                        "field": "field_6225a8a52f16d",
                        "operator": "==",
                        "value": "1"
                    }
                ]
            ],
            "wrapper": {
                "width": "",
                "class": "",
                "id": ""
            },
            "default_value": "",
            "placeholder": "",
            "prepend": "",
            "append": "",
            "maxlength": ""
        },
        {
            "key": "field_63b9a388085b0",
            "label": "Card Footer",
            "name": "card_footer",
            "aria-label": "",
            "type": "wysiwyg",
            "instructions": "",
            "required": 0,
            "conditional_logic": 0,
            "wrapper": {
                "width": "",
                "class": "",
                "id": ""
            },
            "admin_only": 0,
            "default_value": "",
            "tabs": "all",
            "toolbar": "full",
            "media_upload": 1,
            "delay": 0
        },
        {
            "key": "field_6376f420b1ccb",
            "label": "Width",
            "name": "width",
            "aria-label": "",
            "type": "clone",
            "instructions": "",
            "required": 0,
            "conditional_logic": 0,
            "wrapper": {
                "width": "",
                "class": "",
                "id": ""
            },
            "admin_only": 0,
            "clone": [
                "group_6347179ab71c8"
            ],
            "display": "group",
            "layout": "block",
            "prefix_label": 0,
            "prefix_name": 1
        },
        {
            "key": "field_656c160f1be51",
            "label": "Height",
            "name": "height",
            "aria-label": "",
            "type": "clone",
            "instructions": "",
            "required": 0,
            "conditional_logic": 0,
            "wrapper": {
                "width": "",
                "class": "",
                "id": ""
            },
            "admin_only": 0,
            "clone": [
                "group_63473f08f0299"
            ],
            "display": "group",
            "layout": "block",
            "prefix_label": 0,
            "prefix_name": 1
        },
        {
            "key": "field_6376f3be391b2",
            "label": "Margin",
            "name": "margin",
            "aria-label": "",
            "type": "clone",
            "instructions": "",
            "required": 0,
            "conditional_logic": 0,
            "wrapper": {
                "width": "",
                "class": "",
                "id": ""
            },
            "admin_only": 0,
            "clone": [
                "group_6347289eccec8"
            ],
            "display": "group",
            "layout": "block",
            "prefix_label": 0,
            "prefix_name": 1
        },
        {
            "key": "field_6397d3975a96b",
            "label": "Padding",
            "name": "card_padding",
            "aria-label": "",
            "type": "clone",
            "instructions": "",
            "required": 0,
            "conditional_logic": 0,
            "wrapper": {
                "width": "",
                "class": "",
                "id": ""
            },
            "admin_only": 0,
            "clone": [
                "group_634728b1e7498"
            ],
            "display": "group",
            "layout": "block",
            "prefix_label": 0,
            "prefix_name": 1
        },
        {
            "key": "field_6397d2fd5a969",
            "label": "Border Radius",
            "name": "card_border_radius",
            "aria-label": "",
            "type": "clone",
            "instructions": "",
            "required": 0,
            "conditional_logic": 0,
            "wrapper": {
                "width": "",
                "class": "",
                "id": ""
            },
            "admin_only": 0,
            "clone": [
                "group_634db84e5d744"
            ],
            "display": "group",
            "layout": "block",
            "prefix_label": 0,
            "prefix_name": 1
        },
        {
            "key": "field_6397d3425a96a",
            "label": "Box Shadow",
            "name": "card_box_shadow",
            "aria-label": "",
            "type": "clone",
            "instructions": "",
            "required": 0,
            "conditional_logic": 0,
            "wrapper": {
                "width": "",
                "class": "",
                "id": ""
            },
            "admin_only": 0,
            "clone": [
                "group_634db8d0e43e1"
            ],
            "display": "group",
            "layout": "block",
            "prefix_label": 0,
            "prefix_name": 1
        },
        {
            "key": "field_63b7d07a1e171",
            "label": "Horizontal",
            "name": "horizontal",
            "aria-label": "",
            "type": "true_false",
            "instructions": "",
            "required": 0,
            "conditional_logic": 0,
            "wrapper": {
                "width": "",
                "class": "",
                "id": ""
            },
            "admin_only": 0,
            "message": "",
            "default_value": 0,
            "ui_on_text": "",
            "ui_off_text": "",
            "ui": 1
        },
        {
            "key": "field_6367f8db8d9ec",
            "label": "Flip Card",
            "name": "flip_card",
            "aria-label": "",
            "type": "true_false",
            "instructions": "Flip card cannot be used with image overlay.",
            "required": 0,
            "conditional_logic": [
                [
                    {
                        "field": "field_6397e8ebb5465",
                        "operator": "!=",
                        "value": "1"
                    }
                ]
            ],
            "wrapper": {
                "width": "",
                "class": "",
                "id": ""
            },
            "admin_only": 0,
            "message": "",
            "default_value": 0,
            "ui_on_text": "",
            "ui_off_text": "",
            "ui": 1
        },
        {
            "key": "field_63980a8974086",
            "label": "Back Background Image",
            "name": "back_bg_image",
            "aria-label": "",
            "type": "clone",
            "instructions": "",
            "required": 0,
            "conditional_logic": [
                [
                    {
                        "field": "field_6367f8db8d9ec",
                        "operator": "==",
                        "value": "1"
                    }
                ]
            ],
            "wrapper": {
                "width": "",
                "class": "",
                "id": ""
            },
            "admin_only": 0,
            "clone": [
                "group_636871db82c48"
            ],
            "display": "group",
            "layout": "block",
            "prefix_label": 0,
            "prefix_name": 1
        },
        {
            "key": "field_6399041aa99f9",
            "label": "Back Background Color",
            "name": "back_bg_color",
            "aria-label": "",
            "type": "clone",
            "instructions": "",
            "required": 0,
            "conditional_logic": [
                [
                    {
                        "field": "field_6367f8db8d9ec",
                        "operator": "==",
                        "value": "1"
                    }
                ]
            ],
            "wrapper": {
                "width": "",
                "class": "",
                "id": ""
            },
            "admin_only": 0,
            "clone": [
                "group_634653996a829"
            ],
            "display": "group",
            "layout": "block",
            "prefix_label": 0,
            "prefix_name": 1
        },
        {
            "key": "field_656c16771be52",
            "label": "Back Border",
            "name": "card_back_border",
            "aria-label": "",
            "type": "clone",
            "instructions": "",
            "required": 0,
            "conditional_logic": [
                [
                    {
                        "field": "field_6399385883368",
                        "operator": "!=",
                        "value": "1"
                    },
                    {
                        "field": "field_6367f8db8d9ec",
                        "operator": "==",
                        "value": "1"
                    }
                ]
            ],
            "wrapper": {
                "width": "",
                "class": "",
                "id": ""
            },
            "admin_only": 0,
            "clone": [
                "group_634db7f7df7b1"
            ],
            "display": "group",
            "layout": "block",
            "prefix_label": 0,
            "prefix_name": 1
        },
        {
            "key": "field_63990423a99fb",
            "label": "Back Text Color",
            "name": "back_text_color",
            "aria-label": "",
            "type": "clone",
            "instructions": "",
            "required": 0,
            "conditional_logic": [
                [
                    {
                        "field": "field_6367f8db8d9ec",
                        "operator": "==",
                        "value": "1"
                    }
                ]
            ],
            "wrapper": {
                "width": "",
                "class": "",
                "id": ""
            },
            "admin_only": 0,
            "clone": [
                "group_6346513f54d9a"
            ],
            "display": "group",
            "layout": "block",
            "prefix_label": 0,
            "prefix_name": 1
        },
        {
            "key": "field_6367f8f28d9ed",
            "label": "Back Content",
            "name": "card_back_content",
            "aria-label": "",
            "type": "wysiwyg",
            "instructions": "",
            "required": 0,
            "conditional_logic": [
                [
                    {
                        "field": "field_6367f8db8d9ec",
                        "operator": "==",
                        "value": "1"
                    }
                ]
            ],
            "wrapper": {
                "width": "",
                "class": "",
                "id": ""
            },
            "admin_only": 0,
            "default_value": "",
            "tabs": "all",
            "toolbar": "full",
            "media_upload": 1,
            "delay": 0
        },
        {
            "key": "field_6398ea65d689b",
            "label": "Back Border Radius",
            "name": "back_border_radius",
            "aria-label": "",
            "type": "clone",
            "instructions": "",
            "required": 0,
            "conditional_logic": [
                [
                    {
                        "field": "field_6367f8db8d9ec",
                        "operator": "==",
                        "value": "1"
                    }
                ]
            ],
            "wrapper": {
                "width": "",
                "class": "",
                "id": ""
            },
            "admin_only": 0,
            "clone": [
                "group_634db84e5d744"
            ],
            "display": "group",
            "layout": "block",
            "prefix_label": 0,
            "prefix_name": 1
        },
        {
            "key": "field_6397932963277",
            "label": "Featured",
            "name": "featured",
            "aria-label": "",
            "type": "true_false",
            "instructions": "Adds featured class for featured cards in isotope grids.",
            "required": 0,
            "conditional_logic": 0,
            "wrapper": {
                "width": "",
                "class": "",
                "id": ""
            },
            "admin_only": 0,
            "message": "",
            "default_value": 0,
            "ui_on_text": "",
            "ui_off_text": "",
            "ui": 1
        },
        {
            "key": "field_639933b73a520",
            "label": "Remove Card Header Padding",
            "name": "remove_card_header_padding",
            "aria-label": "",
            "type": "true_false",
            "instructions": "",
            "required": 0,
            "conditional_logic": 0,
            "wrapper": {
                "width": "",
                "class": "",
                "id": ""
            },
            "admin_only": 0,
            "message": "",
            "default_value": 0,
            "ui_on_text": "",
            "ui_off_text": "",
            "ui": 1
        },
        {
            "key": "field_639933cf3a521",
            "label": "Remove Card Body Padding",
            "name": "remove_card_body_padding",
            "aria-label": "",
            "type": "true_false",
            "instructions": "",
            "required": 0,
            "conditional_logic": 0,
            "wrapper": {
                "width": "",
                "class": "",
                "id": ""
            },
            "admin_only": 0,
            "message": "",
            "default_value": 0,
            "ui_on_text": "",
            "ui_off_text": "",
            "ui": 1
        },
        {
            "key": "field_6399340c3a523",
            "label": "Remove Card Footer Padding",
            "name": "remove_card_footer_padding",
            "aria-label": "",
            "type": "true_false",
            "instructions": "",
            "required": 0,
            "conditional_logic": 0,
            "wrapper": {
                "width": "",
                "class": "",
                "id": ""
            },
            "admin_only": 0,
            "message": "",
            "default_value": 0,
            "ui_on_text": "",
            "ui_off_text": "",
            "ui": 1
        }
    ],
    "location": [
        [
            {
                "param": "block",
                "operator": "==",
                "value": "acf\/card"
            }
        ]
    ],
    "menu_order": 0,
    "position": "normal",
    "style": "default",
    "label_placement": "top",
    "instruction_placement": "label",
    "hide_on_screen": "",
    "active": true,
    "description": "",
    "show_in_rest": 0,
    "modified": 1759370389
}
